{
  "kind": "collectionType",
  "collectionName": "authors",
  "info": {
    "name": "author",
    "description": ""
  },
  "options": {
    "increments": true,
    "timestamps": true,
    "draftAndPublish": true
  },
  "attributes": {
    "name": {
      "type": "string"
    },
    "about": {
      "type": "text"
    },
    "profile_pic": {
      "model": "file",
      "via": "related",
      "allowedTypes": [
        "images"
      ],
      "plugin": "upload",
      "required": false
    }
  }
}
